plover_trayicon/__init__.py
plover_trayicon/help.py
plover_trayicon-0.0.0.dist-info/LICENSE
plover_trayicon-0.0.0.dist-info/METADATA
plover_trayicon-0.0.0.dist-info/WHEEL
plover_trayicon-0.0.0.dist-info/entry_points.txt
plover_trayicon-0.0.0.dist-info/top_level.txt
plover_trayicon-0.0.0.dist-info/zip-safe
plover_trayicon-0.0.0.dist-info/RECORD
