Metadata-Version: 2.1
Name: plover-trayicon
Version: 0.0.0
Summary: Plover plugin to show a tray icon
Home-page: https://github.com/user202729/plover_trayicon
Author: user202729
License: GNU General Public License v3 or later (GPLv3+)
Keywords: plover plover_plugin
Platform: UNKNOWN
Classifier: Environment :: Plugins
Classifier: License :: OSI Approved :: GNU General Public License v3 or later (GPLv3+)
Classifier: Operating System :: OS Independent
Classifier: Programming Language :: Python :: 3
Requires-Dist: plover (>=4.0.0.dev8)
Requires-Dist: pystray (>=0.17.2)
